safeImport/__init__.py
safeimport-0.8.3.dist-info/METADATA
safeimport-0.8.3.dist-info/WHEEL
safeimport-0.8.3.dist-info/top_level.txt
safeimport-0.8.3.dist-info/RECORD
