Metadata-Version: 2.4
Name: safeImport
Version: 0.8.3
Summary: safeImport Updated Version
Requires-Python: >=3.6
Dynamic: description
Dynamic: description-content-type
Dynamic: requires-python
Dynamic: summary
